<?xml version="1.0"?>
<!DOCTYPE hibernate-mapping PUBLIC "-//Hibernate/Hibernate Mapping DTD 3.0//EN"
"http://hibernate.sourceforge.net/hibernate-mapping-3.0.dtd">
<!-- Generated 2018-9-24 14:44:32 by Hibernate Tools 3.5.0.Final -->
<hibernate-mapping>
    <class name="cn.abc.sshweb1.model.TreeNode" table="sb_treenodes">
        <id name="id" type="int">
            <column name="id" />
            <generator class="native" />
        </id>
        <property name="text" type="java.lang.String">
            <column name="text" />
        </property> 
        <property name="parentId" type="java.lang.Integer">
            <column name="parent_id" />
        </property>
    </class>
</hibernate-mapping>
